albinos/__init__.py
albinos/client.py
albinos/config.py
albinos/controller.py
albinos/error.py
raven_os_albinos-0.0.3.dist-info/DESCRIPTION.rst
raven_os_albinos-0.0.3.dist-info/METADATA
raven_os_albinos-0.0.3.dist-info/RECORD
raven_os_albinos-0.0.3.dist-info/WHEEL
raven_os_albinos-0.0.3.dist-info/metadata.json
raven_os_albinos-0.0.3.dist-info/top_level.txt
