Metadata-Version: 2.0
Name: raven-os-albinos
Version: 0.0.3
Summary: Basic API to interact with albinos daemon
Home-page: https://github.com/raven-os/albinos
Author: Arthur Cros
Author-email: arthur.cros@etna.io
License: UNKNOWN
Platform: UNKNOWN
Classifier: Programming Language :: Python :: 3
